JSONFileOBJDB/__init__.py
JSONFileOBJDB-0.1.0.dist-info/LICENSE.txt
JSONFileOBJDB-0.1.0.dist-info/METADATA
JSONFileOBJDB-0.1.0.dist-info/WHEEL
JSONFileOBJDB-0.1.0.dist-info/top_level.txt
JSONFileOBJDB-0.1.0.dist-info/RECORD
