Metadata-Version: 2.1
Name: JSONFileOBJDB
Version: 0.1.0
Summary: JSON File OBJ DB
Home-page: https://github.com/0187773933/JSONFileOBJDB
Author: win.stitch.23
Author-email: win.stitch.23@gmail.com
License: UNKNOWN
Platform: UNKNOWN
Classifier: Programming Language :: Python :: 3
Classifier: License :: OSI Approved :: MIT License
Classifier: Operating System :: OS Independent
Requires-Python: >=3.6
